[
    {"category": "Search & Reference", "name": "Google", "url": "https://www.google.com", "description": "The world's most popular search engine"},
    {"category": "Search & Reference", "name": "Wikipedia", "url": "https://www.wikipedia.org", "description": "Free online encyclopedia"},
    {"category": "Search & Reference", "name": "Internet Archive", "url": "https://archive.org", "description": "Digital library of free books, websites, and more"},
    {"category": "Search & Reference", "name": "DuckDuckGo", "url": "https://duckduckgo.com", "description": "Privacy-focused search engine"},
    {"category": "Search & Reference", "name": "Wolfram Alpha", "url": "https://www.wolframalpha.com", "description": "Computational knowledge engine"},
    {"category": "Search & Reference", "name": "Google Scholar", "url": "https://scholar.google.com", "description": "Academic research search engine"},
    {"category": "Search & Reference", "name": "Britannica", "url": "https://www.britannica.com", "description": "Comprehensive online encyclopedia"},
    {"category": "Search & Reference", "name": "ScienceDirect", "url": "https://www.sciencedirect.com", "description": "Scientific and medical research database"},
    {"category": "Search & Reference", "name": "Scopus", "url": "https://www.scopus.com", "description": "Abstracts and citations database"},
    {"category": "Search & Reference", "name": "ResearchGate", "url": "https://www.researchgate.net", "description": "Scientific social network"},
    {"category": "Search & Reference", "name": "WorldCat", "url": "https://www.worldcat.org", "description": "Global library catalog"},
    {"category": "Search & Reference", "name": "PubMed", "url": "https://pubmed.ncbi.nlm.nih.gov", "description": "Medical research database"},
    {"category": "Search & Reference", "name": "JSTOR", "url": "https://www.jstor.org", "description": "Digital academic library"},
    {"category": "Search & Reference", "name": "Semantic Scholar", "url": "https://www.semanticscholar.org", "description": "AI-powered research tool"},
    {"category": "Search & Reference", "name": "arXiv", "url": "https://arxiv.org", "description": "Open-access research repository"},
    {"category": "Search & Reference", "name": "Crossref", "url": "https://www.crossref.org", "description": "Academic metadata and linking"},
    {"category": "Search & Reference", "name": "Sci-Hub", "url": "https://sci-hub.se", "description": "Scientific paper access platform"},
    {"category": "Search & Reference", "name": "Google Books", "url": "https://books.google.com", "description": "Digital book library and search"},
    {"category": "Search & Reference", "name": "Bing", "url": "https://www.bing.com", "description": "Microsoft's search engine"},
    {"category": "Search & Reference", "name": "Academic Search Complete", "url": "https://www.ebscohost.com", "description": "Comprehensive academic database"},

    {"category": "Entertainment", "name": "YouTube", "url": "https://www.youtube.com", "description": "Video sharing and streaming platform"},
    {"category": "Entertainment", "name": "Netflix", "url": "https://www.netflix.com", "description": "Streaming service for movies and TV shows"},
    {"category": "Entertainment", "name": "Spotify", "url": "https://www.spotify.com", "description": "Music streaming platform"},
    {"category": "Entertainment", "name": "IMDb", "url": "https://www.imdb.com", "description": "Movie and TV show information database"},
    {"category": "Entertainment", "name": "Twitch", "url": "https://www.twitch.tv", "description": "Live streaming platform for gaming and more"},
    {"category": "Entertainment", "name": "Hulu", "url": "https://www.hulu.com", "description": "Streaming service with TV shows and movies"},
    {"category": "Entertainment", "name": "Disney+", "url": "https://www.disneyplus.com", "description": "Disney, Pixar, Marvel, Star Wars streaming"},
    {"category": "Entertainment", "name": "HBO Max", "url": "https://www.hbomax.com", "description": "Streaming platform for HBO content"},
    {"category": "Entertainment", "name": "Apple Music", "url": "https://www.apple.com/apple-music", "description": "Music streaming service"},
    {"category": "Entertainment", "name": "Pandora", "url": "https://www.pandora.com", "description": "Music streaming and recommendation"},
    {"category": "Entertainment", "name": "Amazon Prime Video", "url": "https://www.amazon.com/Prime-Video", "description": "Video streaming for Prime members"},
    {"category": "Entertainment", "name": "Crunchyroll", "url": "https://www.crunchyroll.com", "description": "Anime streaming platform"},
    {"category": "Entertainment", "name": "Tidal", "url": "https://tidal.com", "description": "High-fidelity music streaming"},
    {"category": "Entertainment", "name": "Letterboxd", "url": "https://letterboxd.com", "description": "Social network for film enthusiasts"},
    {"category": "Entertainment", "name": "Last.fm", "url": "https://www.last.fm", "description": "Music tracking and recommendation"},
    {"category": "Entertainment", "name": "Audible", "url": "https://www.audible.com", "description": "Audiobook streaming platform"},
    {"category": "Entertainment", "name": "Vimeo", "url": "https://vimeo.com", "description": "High-quality video platform"},
    {"category": "Entertainment", "name": "SoundCloud", "url": "https://soundcloud.com", "description": "Music and audio sharing platform"},
    {"category": "Entertainment", "name": "Bandcamp", "url": "https://bandcamp.com", "description": "Music platform for independent artists"},
    {"category": "Entertainment", "name": "Dailymotion", "url": "https://www.dailymotion.com", "description": "Video sharing platform"},

    {"category": "Social Media", "name": "Twitter", "url": "https://www.twitter.com", "description": "Microblogging and social networking platform"},
    {"category": "Social Media", "name": "Facebook", "url": "https://www.facebook.com", "description": "Global social networking site"},
    {"category": "Social Media", "name": "Instagram", "url": "https://www.instagram.com", "description": "Photo and video sharing network"},
    {"category": "Social Media", "name": "LinkedIn", "url": "https://www.linkedin.com", "description": "Professional networking platform"},
    {"category": "Social Media", "name": "Reddit", "url": "https://www.reddit.com", "description": "Community-driven discussion platform"},
    {"category": "Social Media", "name": "TikTok", "url": "https://www.tiktok.com", "description": "Short-form video sharing app"},
    {"category": "Social Media", "name": "Pinterest", "url": "https://www.pinterest.com", "description": "Visual discovery and bookmarking tool"},
    {"category": "Social Media", "name": "Snapchat", "url": "https://www.snapchat.com", "description": "Multimedia messaging app"},
    {"category": "Social Media", "name": "Tumblr", "url": "https://www.tumblr.com", "description": "Blogging and social networking site"},
    {"category": "Social Media", "name": "Discord", "url": "https://discord.com", "description": "Chat platform for communities"},
    {"category": "Social Media", "name": "Mastodon", "url": "https://mastodon.social", "description": "Decentralized social network"},
    {"category": "Social Media", "name": "WhatsApp", "url": "https://www.whatsapp.com", "description": "Secure messaging app"},
    {"category": "Social Media", "name": "Telegram", "url": "https://telegram.org", "description": "Privacy-focused messaging platform"},
    {"category": "Social Media", "name": "WeChat", "url": "https://www.wechat.com", "description": "Multi-purpose messaging app"},
    {"category": "Social Media", "name": "Signal", "url": "https://signal.org", "description": "Encrypted messaging service"},
    {"category": "Social Media", "name": "Viber", "url": "https://www.viber.com", "description": "VoIP and messaging app"},
    {"category": "Social Media", "name": "Flickr", "url": "https://www.flickr.com", "description": "Photo sharing and community platform"},
    {"category": "Social Media", "name": "Meetup", "url": "https://www.meetup.com", "description": "Event organizing and social platform"},
    {"category": "Social Media", "name": "Nextdoor", "url": "https://nextdoor.com", "description": "Neighborhood-based social network"},
    {"category": "Social Media", "name": "Goodreads", "url": "https://www.goodreads.com", "description": "Social network for book lovers"},

    {"category": "News", "name": "CNN", "url": "https://www.cnn.com", "description": "Global news network"},
    {"category": "News", "name": "BBC", "url": "https://www.bbc.com", "description": "British public service broadcaster"},
    {"category": "News", "name": "The New York Times", "url": "https://www.nytimes.com", "description": "American news publication"},
    {"category": "News", "name": "Reuters", "url": "https://www.reuters.com", "description": "International news agency"},
    {"category": "News", "name": "The Guardian", "url": "https://www.theguardian.com", "description": "British news and media outlet"},
    {"category": "News", "name": "Al Jazeera", "url": "https://www.aljazeera.com", "description": "Qatari-funded news network"},
    {"category": "News", "name": "Fox News", "url": "https://www.foxnews.com", "description": "American conservative news channel"},
    {"category": "News", "name": "NPR", "url": "https://www.npr.org", "description": "National Public Radio"},
    {"category": "News", "name": "AP News", "url": "https://www.apnews.com", "description": "Associated Press news service"},
    {"category": "News", "name": "Bloomberg", "url": "https://www.bloomberg.com", "description": "Financial and business news"},
    {"category": "News", "name": "The Wall Street Journal", "url": "https://www.wsj.com", "description": "Business-focused news outlet"},
    {"category": "News", "name": "HuffPost", "url": "https://www.huffpost.com", "description": "Liberal news and opinion site"},
    {"category": "News", "name": "Politico", "url": "https://www.politico.com", "description": "Political journalism platform"},
    {"category": "News", "name": "The Washington Post", "url": "https://www.washingtonpost.com", "description": "American daily newspaper"},
    {"category": "News", "name": "TIME", "url": "https://time.com", "description": "Weekly news magazine"},
    {"category": "News", "name": "The Atlantic", "url": "https://www.theatlantic.com", "description": "American magazine and news site"},
    {"category": "News", "name": "Euronews", "url": "https://www.euronews.com", "description": "European multilingual news"},
    {"category": "News", "name": "DW", "url": "https://www.dw.com", "description": "German international broadcaster"},
    {"category": "News", "name": "CBS News", "url": "https://www.cbsnews.com", "description": "American news broadcasting"},
    {"category": "News", "name": "NBC News", "url": "https://www.nbcnews.com", "description": "National Broadcasting Company news"},

    {"category": "Education", "name": "Khan Academy", "url": "https://www.khanacademy.org", "description": "Free online learning platform"},
    {"category": "Education", "name": "Coursera", "url": "https://www.coursera.org", "description": "Online courses from universities"},
    {"category": "Education", "name": "edX", "url": "https://www.edx.org", "description": "Massive open online courses"},
    {"category": "Education", "name": "Udemy", "url": "https://www.udemy.com", "description": "Online learning marketplace"},
    {"category": "Education", "name": "Duolingo", "url": "https://www.duolingo.com", "description": "Language learning app"},
    {"category": "Education", "name": "Quizlet", "url": "https://quizlet.com", "description": "Study tools and flashcards"},
    {"category": "Education", "name": "TED-Ed", "url": "https://ed.ted.com", "description": "Educational video platform"},
    {"category": "Education", "name": "MIT OpenCourseWare", "url": "https://ocw.mit.edu", "description": "Free MIT course materials"},
    {"category": "Education", "name": "OpenStax", "url": "https://openstax.org", "description": "Free textbooks for education"},
    {"category": "Education", "name": "Class Central", "url": "https://www.classcentral.com", "description": "MOOC discovery platform"},
    {"category": "Education", "name": "FutureLearn", "url": "https://www.futurelearn.com", "description": "Online courses and degrees"},
    {"category": "Education", "name": "Skillshare", "url": "https://www.skillshare.com", "description": "Creative and practical skills courses"},
    {"category": "Education", "name": "Codeacademy", "url": "https://www.codecademy.com", "description": "Interactive coding lessons"},
    {"category": "Education", "name": "Brilliant", "url": "https://brilliant.org", "description": "Problem-solving learning platform"},
    {"category": "Education", "name": "Pluralsight", "url": "https://www.pluralsight.com", "description": "Tech and creative training"},
    {"category": "Education", "name": "MasterClass", "url": "https://www.masterclass.com", "description": "Classes from experts"},
    {"category": "Education", "name": "BBC Learning English", "url": "https://www.bbc.co.uk/learningenglish", "description": "Free English learning resources"},
    {"category": "Education", "name": "Saylor Academy", "url": "https://www.saylor.org", "description": "Free online education"},
    {"category": "Education", "name": "OpenLearn", "url": "https://www.open.edu/openlearn", "description": "Free courses from Open University"},
    {"category": "Education", "name": "Alison", "url": "https://alison.com", "description": "Free online courses and certificates"}
]